ab_service/auth_client/__init__.py
ab_service/auth_client/main.py
ab_service/auth_client/routes/__init__.py
ab_service/auth_client/routes/callback.py
ab_service/auth_client/routes/login.py
ab_auth_client_service-0.2.2.dist-info/METADATA
ab_auth_client_service-0.2.2.dist-info/WHEEL
ab_auth_client_service-0.2.2.dist-info/licenses/LICENSE
ab_auth_client_service-0.2.2.dist-info/RECORD
